sys_prctl/__init__.py
sys_prctl/sys_prctl.so
sys_prctl/t.py
sys_prctl/test_prctl.py
sys_prctl/version_config.py
sys_prctl-0.0.4.dist-info/METADATA
sys_prctl-0.0.4.dist-info/WHEEL
sys_prctl-0.0.4.dist-info/top_level.txt
sys_prctl-0.0.4.dist-info/RECORD
